alarm_reporter.py
claude_analyzer.py
dri_alarm_reporter-0.1.3.dist-info/METADATA
dri_alarm_reporter-0.1.3.dist-info/WHEEL
dri_alarm_reporter-0.1.3.dist-info/entry_points.txt
dri_alarm_reporter-0.1.3.dist-info/top_level.txt
dri_alarm_reporter-0.1.3.dist-info/RECORD
