Metadata-Version: 2.4
Name: dri-alarm-reporter
Version: 0.1.3
Summary: CloudWatch Alarm Daily Reporter with AI-powered root cause analysis
Author-email: Paul Tseng <paul_tseng@trendmicro.com>
License: MIT
Project-URL: Homepage, https://github.com/trendmicro/dri-report
Project-URL: Repository, https://github.com/trendmicro/dri-report
Project-URL: Issues, https://github.com/trendmicro/dri-report/issues
Keywords: aws,cloudwatch,alarms,monitoring,dri,claude,ai-analysis
Classifier: Development Status :: 4 - Beta
Classifier: Intended Audience :: Developers
Classifier: Intended Audience :: System Administrators
Classifier: License :: OSI Approved :: MIT License
Classifier: Programming Language :: Python :: 3
Classifier: Programming Language :: Python :: 3.9
Classifier: Programming Language :: Python :: 3.10
Classifier: Programming Language :: Python :: 3.11
Classifier: Programming Language :: Python :: 3.12
Classifier: Topic :: System :: Monitoring
Requires-Python: >=3.9
Requires-Dist: boto3>=1.26.0
Requires-Dist: anthropic>=0.18.0
Provides-Extra: dev
Requires-Dist: pytest>=7.0.0; extra == "dev"
Requires-Dist: black>=23.0.0; extra == "dev"
Requires-Dist: ruff>=0.1.0; extra == "dev"
